ctrlxdatalayer/__init__.py
ctrlxdatalayer/_version.py
ctrlxdatalayer/bulk.py
ctrlxdatalayer/bulk_util.py
ctrlxdatalayer/clib.py
ctrlxdatalayer/clib_bulk.py
ctrlxdatalayer/clib_client.py
ctrlxdatalayer/clib_converter.py
ctrlxdatalayer/clib_factory.py
ctrlxdatalayer/clib_provider.py
ctrlxdatalayer/clib_provider_node.py
ctrlxdatalayer/clib_system.py
ctrlxdatalayer/clib_variant.py
ctrlxdatalayer/client.py
ctrlxdatalayer/converter.py
ctrlxdatalayer/factory.py
ctrlxdatalayer/metadata_utils.py
ctrlxdatalayer/provider.py
ctrlxdatalayer/provider_node.py
ctrlxdatalayer/provider_subscription.py
ctrlxdatalayer/subscription.py
ctrlxdatalayer/subscription_async.py
ctrlxdatalayer/subscription_properties_builder.py
ctrlxdatalayer/subscription_sync.py
ctrlxdatalayer/system.py
ctrlxdatalayer/variant.py
ctrlx_datalayer-3.4.0.dist-info/METADATA
ctrlx_datalayer-3.4.0.dist-info/MIT.txt
ctrlx_datalayer-3.4.0.dist-info/WHEEL
ctrlx_datalayer-3.4.0.dist-info/boschrexroth_tac_delivery.txt
ctrlx_datalayer-3.4.0.dist-info/tc_for_provision_of_products_free_of_charge.pdf
ctrlx_datalayer-3.4.0.dist-info/top_level.txt
ctrlx_datalayer-3.4.0.dist-info/RECORD
