Metadata-Version: 2.1
Name: ctrlx-datalayer
Version: 3.4.0
Summary: ctrlX Data Layer API for Python
Author-email: Bosch Rexroth AG <github@boschrexroth.com>
Project-URL: Homepage, https://github.com/boschrexroth
Platform: linux
Classifier: Programming Language :: Python :: 3
Classifier: Programming Language :: Python :: 3.8
Classifier: Programming Language :: Python :: 3.10
Classifier: License :: OSI Approved :: MIT License
Classifier: Operating System :: POSIX :: Linux
Requires-Python: >=3.8
License-File: LICENSES/MIT.txt
License-File: LICENSES/boschrexroth_tac_delivery.txt
License-File: LICENSES/tc_for_provision_of_products_free_of_charge.pdf
Requires-Dist: ctrlx_fbs>=2.3.0
Requires-Dist: flatbuffers~=24.3.25
